{
  "response": {
    "header": { "resultCode": "0000", "resultMsg": "OK" },
    "body": {
      "items": {
        "item": [
          {
            "contentid": "1001001",
            "title": "화천산천어축제",
            "contenttypeid": "15",
            "addr1": "강원특별자치도 화천군 화천읍 산천어길 137",
            "addr2": "",
            "areacode": "32",
            "sigungucode": "13",
            "firstimage": "https://tong.visitkorea.or.kr/cms/resource/22/2678622_image2_1.jpg",
            "firstimage2": "https://tong.visitkorea.or.kr/cms/resource/22/2678622_image3_1.jpg",
            "mapx": "127.7086",
            "mapy": "38.1063",
            "eventstartdate": "20251220",
            "eventenddate": "20260131",
            "tel": "033-440-2061",
            "modifiedtime": "20250927180000",
            "createdtime": "20240801100000",
            "cat1": "A02",
            "cat2": "A0207",
            "cat3": "A02070200",
            "mlevel": "6",
            "cpyrhtDivCd": "Type1",
            "zipcode": "24122"
          },
          {
            "contentid": "1001002",
            "title": "평창눈꽃축제",
            "contenttypeid": "15",
            "addr1": "강원특별자치도 평창군 평창읍 평창대로 2993",
            "addr2": "",
            "areacode": "32",
            "sigungucode": "15",
            "firstimage": "https://tong.visitkorea.or.kr/cms/resource/23/2678623_image2_1.jpg",
            "firstimage2": "https://tong.visitkorea.or.kr/cms/resource/23/2678623_image3_1.jpg",
            "mapx": "128.3907",
            "mapy": "37.3704",
            "eventstartdate": "20251215",
            "eventenddate": "20260215",
            "tel": "033-330-2771",
            "modifiedtime": "20250927182000",
            "createdtime": "20240815120000",
            "cat1": "A02",
            "cat2": "A0206",
            "cat3": "A02060100",
            "mlevel": "6",
            "cpyrhtDivCd": "Type2",
            "zipcode": "25927"
          },
          {
            "contentid": "1001003",
            "title": "대관령눈꽃축제",
            "contenttypeid": "15",
            "addr1": "강원특별자치도 평창군 대관령면 횡계리 414",
            "addr2": "",
            "areacode": "32",
            "sigungucode": "15",
            "firstimage": "https://tong.visitkorea.or.kr/cms/resource/24/2678624_image2_1.jpg",
            "firstimage2": "https://tong.visitkorea.or.kr/cms/resource/24/2678624_image3_1.jpg",
            "mapx": "128.7190",
            "mapy": "37.6779",
            "eventstartdate": "20251210",
            "eventenddate": "20260228",
            "tel": "033-335-3995",
            "modifiedtime": "20250927184000",
            "createdtime": "20240901090000",
            "cat1": "A02",
            "cat2": "A0206",
            "cat3": "A02060100",
            "mlevel": "6",
            "cpyrhtDivCd": "Type1",
            "zipcode": "25351"
          },
          {
            "contentid": "1001004",
            "title": "태백산눈축제",
            "contenttypeid": "15",
            "addr1": "강원특별자치도 태백시 태백로 4778",
            "addr2": "(황지동)",
            "areacode": "32",
            "sigungucode": "7",
            "firstimage": "https://tong.visitkorea.or.kr/cms/resource/25/2678625_image2_1.jpg",
            "firstimage2": "https://tong.visitkorea.or.kr/cms/resource/25/2678625_image3_1.jpg",
            "mapx": "128.9856",
            "mapy": "37.1640",
            "eventstartdate": "20260110",
            "eventenddate": "20260220",
            "tel": "033-550-2081",
            "modifiedtime": "20250927190000",
            "createdtime": "20240920110000",
            "cat1": "A02",
            "cat2": "A0206",
            "cat3": "A02060100",
            "mlevel": "6",
            "cpyrhtDivCd": "Type3",
            "zipcode": "26040"
          }
        ]
      },
      "numOfRows": 10,
      "pageNo": 1,
      "totalCount": 4
    }
  }
}
